hamlish_jinja/__init__.py
hamlish_jinja/__main__.py
hamlish_jinja/converter.py
hamlish_jinja/docnode.py
hamlish_jinja/exception.py
hamlish_jinja/extension.py
hamlish_jinja/parser.py
hamlish_jinja/py.typed
Jinja2_Haml-0.3.5.dist-info/AUTHORS
Jinja2_Haml-0.3.5.dist-info/LICENSE
Jinja2_Haml-0.3.5.dist-info/METADATA
Jinja2_Haml-0.3.5.dist-info/WHEEL
Jinja2_Haml-0.3.5.dist-info/entry_points.txt
Jinja2_Haml-0.3.5.dist-info/top_level.txt
Jinja2_Haml-0.3.5.dist-info/RECORD
